mctsnp/__init__.py
mctsnp/mcts.py
mctsnp-0.1.1.dist-info/METADATA
mctsnp-0.1.1.dist-info/WHEEL
mctsnp-0.1.1.dist-info/RECORD
