Metadata-Version: 2.4
Name: mctsnp
Version: 0.1.1
Summary: Monte Carlo Tree Search with Numpy
Requires-Python: >=3.13
Requires-Dist: beartype>=0.20.2
Requires-Dist: jaxtyping>=0.3.2
Requires-Dist: numpy>=2.2.5
